wagtail_footnotes/__init__.py
wagtail_footnotes/apps.py
wagtail_footnotes/blocks.py
wagtail_footnotes/fields.py
wagtail_footnotes/models.py
wagtail_footnotes/urls.py
wagtail_footnotes/wagtail_hooks.py
wagtail_footnotes/widgets.py
wagtail_footnotes/locale/en/LC_MESSAGES/django.mo
wagtail_footnotes/locale/en/LC_MESSAGES/django.po
wagtail_footnotes/locale/fr/LC_MESSAGES/django.mo
wagtail_footnotes/locale/fr/LC_MESSAGES/django.po
wagtail_footnotes/locale/ro/LC_MESSAGES/django.mo
wagtail_footnotes/locale/ro/LC_MESSAGES/django.po
wagtail_footnotes/migrations/0001_initial.py
wagtail_footnotes/migrations/0002_alter_footnote_unique_together.py
wagtail_footnotes/migrations/0003_add_bootstrap_translatable_mixin.py
wagtail_footnotes/migrations/0004_boostrap_translatable_mixin_data_migration.py
wagtail_footnotes/migrations/0005_alter_footnote_locale_alter_footnote_translation_key.py
wagtail_footnotes/migrations/0006_alter_footnote_locale.py
wagtail_footnotes/migrations/0007_alter_footnote_options_footnote_sort_order.py
wagtail_footnotes/migrations/__init__.py
wagtail_footnotes/static/footnotes/js/footnotes.js
wagtail_footnotes/static/footnotes/js/read-only-uuid-controller.js
wagtail_footnotes/templates/wagtail_footnotes/admin/footnotes_modal.html
wagtail_footnotes/templates/wagtail_footnotes/includes/footnote_reference.html
wagtail_footnotes/templates/wagtail_footnotes/includes/footnotes.html
wagtail_footnotes-0.14.0.dist-info/licenses/LICENSE
wagtail_footnotes-0.14.0.dist-info/WHEEL
wagtail_footnotes-0.14.0.dist-info/METADATA
wagtail_footnotes-0.14.0.dist-info/RECORD
