Metadata-Version: 2.4
Name: wagtail-footnotes
Version: 0.14.0
Summary: Add footnotes to rich text in your Wagtail pages
Keywords: Wagtail,Django,footnotes,rich text
Author-email: Cameron Lamb  <hello@torchbox.com>
Maintainer-email: Kevin Howbrook <kevin.howbrook@torchbox.com>, Dan Braghis <dan.braghis@torchbox.com>
Requires-Python: >=3.9
Classifier: Development Status :: 4 - Beta
Classifier: Environment :: Web Environment
Classifier: Intended Audience :: Developers
Classifier: Operating System :: OS Independent
Classifier: License :: OSI Approved :: MIT License
Classifier: Programming Language :: Python
Classifier: Programming Language :: Python :: 3
Classifier: Programming Language :: Python :: 3.9
Classifier: Programming Language :: Python :: 3.10
Classifier: Programming Language :: Python :: 3.11
Classifier: Programming Language :: Python :: 3.12
Classifier: Programming Language :: Python :: 3.13
Classifier: Framework :: Django
Classifier: Framework :: Django :: 4.2
Classifier: Framework :: Django :: 5.1
Classifier: Framework :: Django :: 5.2
Classifier: Framework :: Wagtail
Classifier: Framework :: Wagtail :: 6
Classifier: Framework :: Wagtail :: 7
License-File: LICENSE
Requires-Dist: Wagtail>=6.3
Requires-Dist: Django>=4.2
Requires-Dist: pre-commit>=4.3 ; extra == "testing"
Requires-Dist: tox>=4.22,<5 ; extra == "testing"
Requires-Dist: coverage>=7.10.6,<8.0 ; extra == "testing"
Requires-Dist: wagtail-modeladmin>=2.0.0 ; extra == "testing"
Project-URL: Changelog, https://github.com/torchbox/wagtail-footnotes/blob/main/CHANGELOG.md
Project-URL: Repository, https://github.com/torchbox/wagtail-footnotes
Provides-Extra: testing
